textformater/__init__.py
textformater/cli.py
textformater/config.py
textformater/polish.py
textformater/processors.py
text_formater-0.1.1.dist-info/LICENSE
text_formater-0.1.1.dist-info/METADATA
text_formater-0.1.1.dist-info/WHEEL
text_formater-0.1.1.dist-info/entry_points.txt
text_formater-0.1.1.dist-info/top_level.txt
text_formater-0.1.1.dist-info/RECORD
