Metadata-Version: 2.1
Name: text-formater
Version: 0.1.1
Summary: A CLI tool for polishing text with Chinese typography rules
Author-email: lixiaolai <xiaolaidev@gmail.com>
License: MIT
Project-URL: Homepage, https://github.com/xiaolai/text-formater
Project-URL: Repository, https://github.com/xiaolai/text-formater
Project-URL: Issues, https://github.com/xiaolai/text-formater/issues
Keywords: text,formatter,chinese,typography,cjk,cli
Classifier: Development Status :: 4 - Beta
Classifier: Intended Audience :: Developers
Classifier: Intended Audience :: End Users/Desktop
Classifier: Operating System :: OS Independent
Classifier: Programming Language :: Python :: 3
Classifier: Programming Language :: Python :: 3.8
Classifier: Programming Language :: Python :: 3.9
Classifier: Programming Language :: Python :: 3.10
Classifier: Programming Language :: Python :: 3.11
Classifier: Programming Language :: Python :: 3.12
Classifier: Topic :: Text Processing
Classifier: Topic :: Text Processing :: Filters
Classifier: Topic :: Software Development :: Libraries :: Python Modules
Requires-Python: >=3.8
License-File: LICENSE
Requires-Dist: click>=8.0
Provides-Extra: dev
Requires-Dist: pytest>=7.0; extra == "dev"
Requires-Dist: pytest-cov>=4.0; extra == "dev"
Provides-Extra: html
Requires-Dist: beautifulsoup4>=4.11; extra == "html"
Requires-Dist: lxml>=4.9; extra == "html"
